[{"school_id":"119","province_id":"14","type":"1","batch":"51","zslx":"0","xclevel":"0","max":"-","min_section":"4602","min":"620","average":"-","filing":"620","first_km":"0","local_batch_name":"本科一批A段","zslx_name":"普通类","xclevel_name":"-","sg_fxk":"","sg_sxk":"","sg_type":"","sg_name":"","sg_info":"","proscore":"537","year":"2020"},{"school_id":"119","province_id":"14","type":"1","batch":"98","zslx":"0","xclevel":"0","max":"-","min_section":"9154","min":"598","average":"-","filing":"598","first_km":"0","local_batch_name":"本科一批A1段","zslx_name":"普通类","xclevel_name":"-","sg_fxk":"","sg_sxk":"","sg_type":"","sg_name":"","sg_info":"","proscore":"537","year":"2020"}]